energymetadata/__init__.py
energymetadata/energymetadata.py
energymetadata-0.0.3.dist-info/LICENSE
energymetadata-0.0.3.dist-info/METADATA
energymetadata-0.0.3.dist-info/WHEEL
energymetadata-0.0.3.dist-info/top_level.txt
energymetadata-0.0.3.dist-info/RECORD
