Metadata-Version: 2.1
Name: energymetadata
Version: 0.0.3
Summary: Retrieve metadata for your energy project' location
Home-page: UNKNOWN
Author: Julian Ascencio-Vasquez
License: UNKNOWN
Platform: UNKNOWN
License-File: LICENSE
